typefit/__init__.py
typefit/api.py
typefit/compat.py
typefit/fitting.py
typefit/httpx_models.py
typefit/meta.py
typefit/narrows.py
typefit/nodes.py
typefit/reporting.py
typefit/serialize.py
typefit/utils.py
typefit-1.0.0.dist-info/LICENSE
typefit-1.0.0.dist-info/METADATA
typefit-1.0.0.dist-info/WHEEL
typefit-1.0.0.dist-info/RECORD
