Metadata-Version: 2.1
Name: typefit
Version: 1.0.0
Summary: Fits JSON values into Python type-anotated objects
Home-page: https://github.com/Xowap/typefit/
License: WTFPL
Keywords: typing,json,api
Author: Rémy Sanchez
Author-email: remy.sanchez@hyperthese.net
Requires-Python: >=3.10,<4.0
Classifier: License :: Other/Proprietary License
Classifier: Programming Language :: Python :: 3
Classifier: Programming Language :: Python :: 3.10
Classifier: Programming Language :: Python :: 3.11
Classifier: Programming Language :: Python :: 3.12
Requires-Dist: httpx (>=0.22,<2.0.0)
Requires-Dist: pendulum (>=3.0.0,<4.0.0)
Requires-Dist: pygments (<3.0.0)
Project-URL: Repository, https://github.com/Xowap/typefit/
